server.py
streamdeck_mcp-0.1.2.dist-info/METADATA
streamdeck_mcp-0.1.2.dist-info/WHEEL
streamdeck_mcp-0.1.2.dist-info/licenses/LICENSE
streamdeck_mcp-0.1.2.dist-info/RECORD
