Metadata-Version: 2.4
Name: streamdeck-mcp
Version: 0.1.2
Summary: MCP server for Elgato Stream Deck control — set buttons, manage pages, wire actions
Author: Jack Arturo
License: MIT
License-File: LICENSE
Requires-Python: >=3.11
Requires-Dist: mcp[cli]>=1.6.0
Requires-Dist: pillow>=10.0.0
Requires-Dist: streamdeck>=0.9.0
Provides-Extra: dev
Requires-Dist: pytest-asyncio>=0.21.0; extra == 'dev'
Requires-Dist: pytest>=7.0; extra == 'dev'
Requires-Dist: ruff; extra == 'dev'
